ase_db_backends/__init__.py
ase_db_backends/_sqlite.py
ase_db_backends/aselmdb.py
ase_db_backends/mysql.py
ase_db_backends/postgresql.py
ase_db_backends/tests/__init__.py
ase_db_backends/tests/conftest.py
ase_db_backends/tests/test_aselmdb_concurrency.py
ase_db_backends/tests/test_db.py
ase_db_backends/tests/test_db2.py
ase_db_backends/tests/test_mysql.py
ase_db_backends/tests/test_sql_db_ext_tables.py
ase_db_backends-0.11.0.dist-info/licenses/COPYING
ase_db_backends-0.11.0.dist-info/licenses/COPYING.LESSER
ase_db_backends-0.11.0.dist-info/licenses/LICENSE
ase_db_backends-0.11.0.dist-info/METADATA
ase_db_backends-0.11.0.dist-info/WHEEL
ase_db_backends-0.11.0.dist-info/top_level.txt
ase_db_backends-0.11.0.dist-info/RECORD
